py_make_weekly_report_kace_rni/__init__.py
py_make_weekly_report_kace_rni/__main__.py
py_make_weekly_report_kace_rni-0.1.2.dist-info/licenses/LICENSE
py_make_weekly_report_kace_rni-0.1.2.dist-info/METADATA
py_make_weekly_report_kace_rni-0.1.2.dist-info/WHEEL
py_make_weekly_report_kace_rni-0.1.2.dist-info/entry_points.txt
py_make_weekly_report_kace_rni-0.1.2.dist-info/top_level.txt
py_make_weekly_report_kace_rni-0.1.2.dist-info/RECORD
