Metadata-Version: 2.4
Name: py_make_weekly_report_kace_rni
Version: 0.1.2
Summary: CLI to generate weekly report
Author-email: Anthony Asamoah <anthonyasamoah48@gmail.com>
License-Expression: MIT
Project-URL: Homepage, https://github.com/Anthony-Asamoah/py_make_weekly_report_kace_rni
Project-URL: Bug Tracker, https://github.com/Anthony-Asamoah/py_make_weekly_report_kace_rni/issues
Classifier: Programming Language :: Python :: 3
Classifier: Operating System :: OS Independent
Requires-Python: >=3.7
License-File: LICENSE
Requires-Dist: rich
Requires-Dist: pyperclip
Dynamic: license-file
